Metadata-Version: 2.1
Name: example-package-pypi
Version: 1.0.0
Summary: A useful module
Home-page: https://code.alipay.com/caichu.fh/pypi-demo
Author: Cai Chu
Author-email: caichu.fh@antgroup.com
License: UNKNOWN
Project-URL: Bug Tracker, https://code.alipay.com/caichu.fh/pypi-demo/issues
Platform: any
Classifier: Programming Language :: Python :: 3
Classifier: License :: OSI Approved :: MIT License
Classifier: Operating System :: OS Independent
Requires-Python: >=3.6
License-File: LICENSE
